asari/__init__.py
asari/api.py
asari/data/pipeline.onnx
asari/preprocess.py
asari/train.py
asari-0.2.0.dist-info/LICENSE
asari-0.2.0.dist-info/WHEEL
asari-0.2.0.dist-info/METADATA
asari-0.2.0.dist-info/RECORD
